geolink_formatter/__init__.py
geolink_formatter/entity.py
geolink_formatter/format.py
geolink_formatter/parser.py
geolink_formatter/utils.py
geolink_formatter/schema/v1.0.0.xsd
geolink_formatter/schema/v1.1.0.xsd
geolink_formatter/schema/v1.1.1.xsd
geolink_formatter/schema/v1.2.0.xsd
geolink_formatter/schema/v1.2.1.xsd
geolink_formatter/schema/v1.2.2.xsd
geolink_formatter/schema/v1.2.3.xsd
geolink_formatter/schema/v1.2.4.xsd
geolink_formatter/schema/v1.2.5.xsd
geolink_formatter/schema/v1.2.6.xsd
geolink_formatter-2.0.7.dist-info/licenses/LICENSE
geolink_formatter-2.0.7.dist-info/METADATA
geolink_formatter-2.0.7.dist-info/WHEEL
geolink_formatter-2.0.7.dist-info/top_level.txt
geolink_formatter-2.0.7.dist-info/RECORD
