Metadata-Version: 2.4
Name: geolink_formatter
Version: 2.0.7
Summary: OEREBlex geoLink Formatter
Home-page: https://gitlab.com/gf-bl/python-geolink-formatter
Author: Karsten Deininger
Author-email: karsten.deininger@bl.ch
License: BSD
Keywords: oereb lex geolink formatter html
Classifier: Development Status :: 5 - Production/Stable
Classifier: Intended Audience :: Developers
Classifier: License :: OSI Approved :: BSD License
Classifier: Natural Language :: English
Classifier: Operating System :: OS Independent
Classifier: Programming Language :: Python :: 3.9
Classifier: Programming Language :: Python :: 3.10
Classifier: Programming Language :: Python :: 3.11
Classifier: Programming Language :: Python :: 3.12
Classifier: Topic :: Scientific/Engineering :: GIS
Classifier: Topic :: Software Development :: Libraries :: Python Modules
License-File: LICENSE
Requires-Dist: lxml>=5.4.0
Requires-Dist: defusedxml
Requires-Dist: requests
Requires-Dist: xmlschema
Dynamic: author
Dynamic: author-email
Dynamic: classifier
Dynamic: description
Dynamic: home-page
Dynamic: keywords
Dynamic: license
Dynamic: license-file
Dynamic: requires-dist
Dynamic: summary
